[
  {
    "標題": "學年期：1141 系所名稱:獸醫學系學士班 年級:1 班別:B",
    "必選別": "必修",
    "選課號碼": "1116",
    "科目名稱": "普通動物學 b\nGeneral Zoology",
    "先修科目": "",
    "全半年": "半",
    "學分數": "2",
    "上課時數": "2",
    "實習時數": "",
    "上課時間": "456",
    "實習時間": "",
    "上課教室": "QB108",
    "實習教室": "",
    "上課教師": "劉新梧等",
    "實習教師": "",
    "開課單位": "獸醫系",
    "開課人數": "90",
    "外系人數": "0",
    "可加選餘額": "90",
    "授課語言": "中/英文",
    "備註": "使用全英文課綱、教材與評量方式Syllabus, teaching materials and assessment methods are all in english"
  },
  {
    "標題": "學年期：1141 系所名稱:獸醫學系學士班 年級:1 班別:B",
    "必選別": "選修",
    "選課號碼": "1118",
    "科目名稱": "獸醫學概論 b\nIntroduction to Veterinary Science",
    "先修科目": "",
    "全半年": "半",
    "學分數": "1",
    "上課時數": "1",
    "實習時數": "",
    "上課時間": "23",
    "實習時間": "",
    "上課教室": "QB1101",
    "實習教室": "",
    "上課教師": "陳文英",
    "實習教師": "",
    "開課單位": "獸醫系",
    "開課人數": "80",
    "外系人數": "",
    "可加選餘額": "80",
    "授課語言": "中文",
    "備註": "Z"
  },
  {
    "標題": "學年期：1141 系所名稱:獸醫學系學士班 年級:1 班別:B",
    "必選別": "必修",
    "選課號碼": "1120",
    "科目名稱": "獸醫解剖學 b\nVeterinary Anatomy",
    "先修科目": "",
    "全半年": "全",
    "學分數": "2",
    "上課時數": "2",
    "實習時數": "",
    "上課時間": "15,31",
    "實習時間": "",
    "上課教室": "QA115",
    "實習教室": "",
    "上課教師": "陳建榮",
    "實習教師": "",
    "開課單位": "獸醫系",
    "開課人數": "60",
    "外系人數": "",
    "可加選餘額": "60",
    "授課語言": "中文",
    "備註": ""
  },
  {
    "標題": "學年期：1141 系所名稱:獸醫學系學士班 年級:1 班別:B",
    "必選別": "必修",
    "選課號碼": "1122",
    "科目名稱": "獸醫解剖學實習 b\nVeterinary Anatomy and Practice",
    "先修科目": "",
    "全半年": "全",
    "學分數": "2",
    "上課時數": "",
    "實習時數": "6",
    "上課時間": "",
    "實習時間": "1678,3234",
    "上課教室": "",
    "實習教室": "QA115",
    "上課教師": "",
    "實習教師": "陳建榮",
    "開課單位": "獸醫系",
    "開課人數": "60",
    "外系人數": "",
    "可加選餘額": "60",
    "授課語言": "中文",
    "備註": ""
  },
  {
    "標題": "學年期：1141 系所名稱:獸醫學系學士班 年級:1 班別:B",
    "必選別": "必修",
    "選課號碼": "1160",
    "科目名稱": "普通化學實驗 f\nGeneral Chemistry and Lab",
    "先修科目": "",
    "全半年": "半",
    "學分數": "1",
    "上課時數": "",
    "實習時數": "3",
    "上課時間": "",
    "實習時間": "5234",
    "上課教室": "",
    "實習教室": "T310",
    "上課教師": "",
    "實習教師": "待聘",
    "開課單位": "化學系",
    "開課人數": "80",
    "外系人數": "",
    "可加選餘額": "80",
    "授課語言": "中文",
    "備註": ""
  },
  {
    "標題": "學年期：1141 系所名稱:獸醫學系學士班 年級:1 班別:B",
    "必選別": "必修",
    "選課號碼": "1170",
    "科目名稱": "普通化學 c\nGeneral Chemistry",
    "先修科目": "",
    "全半年": "半",
    "學分數": "3",
    "上課時數": "3",
    "實習時數": "",
    "上課時間": "434,51",
    "實習時間": "",
    "上課教室": "QE304",
    "實習教室": "",
    "上課教師": "蕭鶴軒",
    "實習教師": "",
    "開課單位": "化學系",
    "開課人數": "96",
    "外系人數": "",
    "可加選餘額": "96",
    "授課語言": "中文",
    "備註": ""
  },
  {
    "標題": "學年期：1141 系所名稱:獸醫學系學士班 年級:1 班別:B",
    "必選別": "必修",
    "選課號碼": "1197",
    "科目名稱": "動物福利學 b\nAnimal Welfare",
    "先修科目": "",
    "全半年": "半",
    "學分數": "2",
    "上課時數": "2",
    "實習時數": "",
    "上課時間": "289",
    "實習時間": "",
    "上課教室": "QE304",
    "實習教室": "",
    "上課教師": "鄧紫云",
    "實習教師": "",
    "開課單位": "獸醫系",
    "開課人數": "100",
    "外系人數": "0",
    "可加選餘額": "100",
    "授課語言": "中文",
    "備註": ""
  },
  {
    "標題": "學年期：1141 系所名稱:獸醫學系學士班 年級:2 班別:B",
    "必選別": "選修",
    "選課號碼": "2153",
    "科目名稱": "動物飼養管理學 a\nFeeding and Management of Domestic Animal",
    "先修科目": "",
    "全半年": "半",
    "學分數": "2",
    "上課時數": "2",
    "實習時數": "",
    "上課時間": "456",
    "實習時間": "",
    "上課教室": "I104",
    "實習教室": "",
    "上課教師": "李滋泰等",
    "實習教師": "",
    "開課單位": "動科系",
    "開課人數": "120",
    "外系人數": "",
    "可加選餘額": "120",
    "授課語言": "中文",
    "備註": "Z"
  },
  {
    "標題": "學年期：1141 系所名稱:獸醫學系學士班 年級:2 班別:B",
    "必選別": "選修",
    "選課號碼": "2159",
    "科目名稱": "獸醫基礎科學概論(一) a\nFundamentals in Veterinary Basic Science(I)",
    "先修科目": "",
    "全半年": "半",
    "學分數": "2",
    "上課時數": "2",
    "實習時數": "",
    "上課時間": "434",
    "實習時間": "",
    "上課教室": "QA001",
    "實習教室": "",
    "上課教師": "劉浩屏等",
    "實習教師": "",
    "開課單位": "獸醫系",
    "開課人數": "73",
    "外系人數": "",
    "可加選餘額": "73",
    "授課語言": "中文",
    "備註": "Z"
  },
  {
    "標題": "學年期：1141 系所名稱:獸醫學系學士班 年級:2 班別:B",
    "必選別": "必修",
    "選課號碼": "2161",
    "科目名稱": "獸醫生理學 b\nVeterinary Physiology",
    "先修科目": "",
    "全半年": "全",
    "學分數": "3",
    "上課時數": "3",
    "實習時數": "",
    "上課時間": "5234",
    "實習時間": "",
    "上課教室": "QB101",
    "實習教室": "",
    "上課教師": "毛嘉洪等",
    "實習教師": "",
    "開課單位": "獸醫系",
    "開課人數": "60",
    "外系人數": "",
    "可加選餘額": "60",
    "授課語言": "中文",
    "備註": ""
  },
  {
    "標題": "學年期：1141 系所名稱:獸醫學系學士班 年級:2 班別:B",
    "必選別": "必修",
    "選課號碼": "2162",
    "科目名稱": "獸醫寄生蟲學 a\nVeterinary Parasitology",
    "先修科目": "",
    "全半年": "半",
    "學分數": "2",
    "上課時數": "2",
    "實習時數": "",
    "上課時間": "234",
    "實習時間": "",
    "上課教室": "QB108",
    "實習教室": "",
    "上課教師": "賴政宏等",
    "實習教師": "",
    "開課單位": "獸醫系",
    "開課人數": "120",
    "外系人數": "",
    "可加選餘額": "120",
    "授課語言": "中文",
    "備註": "Z"
  },
  {
    "標題": "學年期：1141 系所名稱:獸醫學系學士班 年級:2 班別:B",
    "必選別": "必修",
    "選課號碼": "2163",
    "科目名稱": "獸醫細菌學\nVererinary Bacteriology",
    "先修科目": "",
    "全半年": "半",
    "學分數": "2",
    "上課時數": "2",
    "實習時數": "",
    "上課時間": "334",
    "實習時間": "",
    "上課教室": "QE304",
    "實習教室": "",
    "上課教師": "郭致榮",
    "實習教師": "",
    "開課單位": "獸醫系",
    "開課人數": "102",
    "外系人數": "0",
    "可加選餘額": "102",
    "授課語言": "中文",
    "備註": "Z"
  },
  {
    "標題": "學年期：1141 系所名稱:獸醫學系學士班 年級:2 班別:B",
    "必選別": "必修",
    "選課號碼": "2166",
    "科目名稱": "獸醫病毒學 b\nVeterinary Virology",
    "先修科目": "",
    "全半年": "半",
    "學分數": "2",
    "上課時數": "2",
    "實習時數": "",
    "上課時間": "312",
    "實習時間": "",
    "上課教室": "QE304",
    "實習教室": "",
    "上課教師": "王之仰等",
    "實習教師": "",
    "開課單位": "獸醫系",
    "開課人數": "60",
    "外系人數": "",
    "可加選餘額": "60",
    "授課語言": "中文",
    "備註": ""
  },
  {
    "標題": "學年期：1141 系所名稱:獸醫學系學士班 年級:2 班別:B",
    "必選別": "必修",
    "選課號碼": "2170",
    "科目名稱": "獸醫生理學實習 b\nVeterinary Physiology Lab.",
    "先修科目": "",
    "全半年": "半",
    "學分數": "1",
    "上課時數": "",
    "實習時數": "3",
    "上課時間": "",
    "實習時間": "2567",
    "上課教室": "",
    "實習教室": "QB201",
    "上課教師": "",
    "實習教師": "陳柏文等",
    "開課單位": "獸醫系",
    "開課人數": "80",
    "外系人數": "",
    "可加選餘額": "80",
    "授課語言": "中文",
    "備註": ""
  },
  {
    "標題": "學年期：1141 系所名稱:獸醫學系學士班 年級:2 班別:B",
    "必選別": "必修",
    "選課號碼": "2172",
    "科目名稱": "獸醫病毒學實習 b\nLab of Veterinary Virology",
    "先修科目": "",
    "全半年": "半",
    "學分數": "1",
    "上課時數": "",
    "實習時數": "3",
    "上課時間": "",
    "實習時間": "1567",
    "上課教室": "",
    "實習教室": "QE303",
    "上課教師": "",
    "實習教師": "劉浩屏等",
    "開課單位": "獸醫系",
    "開課人數": "60",
    "外系人數": "",
    "可加選餘額": "60",
    "授課語言": "中文",
    "備註": ""
  },
  {
    "標題": "學年期：1141 系所名稱:獸醫學系學士班 年級:2 班別:B",
    "必選別": "必修",
    "選課號碼": "2174",
    "科目名稱": "獸醫細菌學實習 b\nVeterinary Bacteriology Lab.",
    "先修科目": "",
    "全半年": "半",
    "學分數": "1",
    "上課時數": "",
    "實習時數": "3",
    "上課時間": "",
    "實習時間": "3567",
    "上課教室": "",
    "實習教室": "QE303",
    "上課教師": "",
    "實習教師": "郭致榮",
    "開課單位": "獸醫系",
    "開課人數": "60",
    "外系人數": "",
    "可加選餘額": "60",
    "授課語言": "中文",
    "備註": ""
  },
  {
    "標題": "學年期：1141 系所名稱:獸醫學系學士班 年級:2 班別:B",
    "必選別": "必修",
    "選課號碼": "2176",
    "科目名稱": "獸醫寄生蟲學實習 b\nVeterinary Parasitology Lab.",
    "先修科目": "",
    "全半年": "半",
    "學分數": "1",
    "上課時數": "",
    "實習時數": "3",
    "上課時間": "",
    "實習時間": "5567",
    "上課教室": "",
    "實習教室": "QE302",
    "上課教師": "",
    "實習教師": "賴政宏等",
    "開課單位": "獸醫系",
    "開課人數": "52",
    "外系人數": "0",
    "可加選餘額": "52",
    "授課語言": "中文",
    "備註": ""
  },
  {
    "標題": "學年期：1141 系所名稱:獸醫學系學士班 年級:2 班別:B",
    "必選別": "必修",
    "選課號碼": "2179",
    "科目名稱": "醫用生物化學 Z\nMedical Biochemistry",
    "先修科目": "",
    "全半年": "全",
    "學分數": "2",
    "上課時數": "2",
    "實習時數": "",
    "上課時間": "412",
    "實習時間": "",
    "上課教室": "QE304",
    "實習教室": "",
    "上課教師": "劉浩屏等",
    "實習教師": "",
    "開課單位": "獸醫系",
    "開課人數": "110",
    "外系人數": "0",
    "可加選餘額": "110",
    "授課語言": "中文",
    "備註": "Z"
  },
  {
    "標題": "學年期：1141 系所名稱:獸醫學系學士班 年級:3 班別:B",
    "必選別": "選修",
    "選課號碼": "3105",
    "科目名稱": "動物疫苗之理論與實際 b\nThe Principles and Practice of Animal Vaccination",
    "先修科目": "",
    "全半年": "半",
    "學分數": "2",
    "上課時數": "2",
    "實習時數": "",
    "上課時間": "534",
    "實習時間": "",
    "上課教室": "QB201",
    "實習教室": "",
    "上課教師": "張佳瑜",
    "實習教師": "",
    "開課單位": "獸醫系",
    "開課人數": "30",
    "外系人數": "",
    "可加選餘額": "30",
    "授課語言": "中/英文",
    "備註": "使用全英文課綱、教材與評量方式Syllabus, teaching materials and assessment methods are all in english"
  },
  {
    "標題": "學年期：1141 系所名稱:獸醫學系學士班 年級:3 班別:B",
    "必選別": "選修",
    "選課號碼": "3120",
    "科目名稱": "獸醫社會實踐 b\nVeterinary Social Practice",
    "先修科目": "",
    "全半年": "半",
    "學分數": "2",
    "上課時數": "2",
    "實習時數": "",
    "上課時間": "478",
    "實習時間": "",
    "上課教室": "QB108",
    "實習教室": "",
    "上課教師": "林荀龍",
    "實習教師": "",
    "開課單位": "獸醫系",
    "開課人數": "70",
    "外系人數": "",
    "可加選餘額": "70",
    "授課語言": "中文",
    "備註": "Z"
  },
  {
    "標題": "學年期：1141 系所名稱:獸醫學系學士班 年級:3 班別:B",
    "必選別": "選修",
    "選課號碼": "3149",
    "科目名稱": "病態生理學 b\nPathophysiology",
    "先修科目": "",
    "全半年": "半",
    "學分數": "2",
    "上課時數": "2",
    "實習時數": "",
    "上課時間": "212",
    "實習時間": "",
    "上課教室": "QB108",
    "實習教室": "",
    "上課教師": "許筑甯",
    "實習教師": "",
    "開課單位": "獸醫系",
    "開課人數": "35",
    "外系人數": "10",
    "可加選餘額": "35",
    "授課語言": "中/英文",
    "備註": "使用全英文課綱、教材與評量方式Syllabus, teaching materials and assessment methods are all in english"
  },
  {
    "標題": "學年期：1141 系所名稱:獸醫學系學士班 年級:3 班別:B",
    "必選別": "必修",
    "選課號碼": "3166",
    "科目名稱": "動物傳染病學 b\nInfectious Diseases of Domestic Animals",
    "先修科目": "",
    "全半年": "全",
    "學分數": "2",
    "上課時數": "2",
    "實習時數": "",
    "上課時間": "434",
    "實習時間": "",
    "上課教室": "QB1101",
    "實習教室": "",
    "上課教師": "賈敏原等",
    "實習教師": "",
    "開課單位": "獸醫系",
    "開課人數": "120",
    "外系人數": "",
    "可加選餘額": "120",
    "授課語言": "中文",
    "備註": ""
  },
  {
    "標題": "學年期：1141 系所名稱:獸醫學系學士班 年級:3 班別:B",
    "必選別": "選修",
    "選課號碼": "3175",
    "科目名稱": "小動物臨床營養學 a\nSmall Animal Clinical Nutriology",
    "先修科目": "",
    "全半年": "半",
    "學分數": "2",
    "上課時數": "2",
    "實習時數": "",
    "上課時間": "556",
    "實習時間": "",
    "上課教室": "QA001",
    "實習教室": "",
    "上課教師": "張力天",
    "實習教師": "",
    "開課單位": "獸醫系",
    "開課人數": "31",
    "外系人數": "",
    "可加選餘額": "70",
    "授課語言": "中文",
    "備註": "Z"
  },
  {
    "標題": "學年期：1141 系所名稱:獸醫學系學士班 年級:3 班別:B",
    "必選別": "必修",
    "選課號碼": "3178",
    "科目名稱": "獸醫產科及繁殖障礙學 a\nVeterinary Reproductive Disorders and Obstetrics",
    "先修科目": "",
    "全半年": "半",
    "學分數": "3",
    "上課時數": "3",
    "實習時數": "",
    "上課時間": "1567",
    "實習時間": "",
    "上課教室": "QE304",
    "實習教室": "",
    "上課教師": "陳鵬文",
    "實習教師": "",
    "開課單位": "獸醫系",
    "開課人數": "120",
    "外系人數": "",
    "可加選餘額": "120",
    "授課語言": "中文",
    "備註": "Z"
  },
  {
    "標題": "學年期：1141 系所名稱:獸醫學系學士班 年級:3 班別:B",
    "必選別": "必修",
    "選課號碼": "3180",
    "科目名稱": "獸醫病理學實習 b\nLab of Veterinary Pathology",
    "先修科目": "",
    "全半年": "全",
    "學分數": "1",
    "上課時數": "",
    "實習時數": "3",
    "上課時間": "",
    "實習時間": "2567",
    "上課教室": "",
    "實習教室": "QB203",
    "上課教師": "",
    "實習教師": "邱慧英等",
    "開課單位": "獸醫系",
    "開課人數": "60",
    "外系人數": "",
    "可加選餘額": "60",
    "授課語言": "中文",
    "備註": ""
  },
  {
    "標題": "學年期：1141 系所名稱:獸醫學系學士班 年級:3 班別:B",
    "必選別": "必修",
    "選課號碼": "3183",
    "科目名稱": "獸醫病理學 a\nVeterinary Pathology",
    "先修科目": "",
    "全半年": "全",
    "學分數": "3",
    "上課時數": "3",
    "實習時數": "",
    "上課時間": "1234",
    "實習時間": "",
    "上課教室": "QE304",
    "實習教室": "",
    "上課教師": "邱慧英等",
    "實習教師": "",
    "開課單位": "獸醫系",
    "開課人數": "120",
    "外系人數": "",
    "可加選餘額": "120",
    "授課語言": "中文",
    "備註": "Z"
  },
  {
    "標題": "學年期：1141 系所名稱:獸醫學系學士班 年級:3 班別:B",
    "必選別": "必修",
    "選課號碼": "3184",
    "科目名稱": "獸醫藥理學 b\nVeterinary Pharmacology",
    "先修科目": "",
    "全半年": "全",
    "學分數": "3",
    "上課時數": "3",
    "實習時數": "",
    "上課時間": "3234",
    "實習時間": "",
    "上課教室": "QB1101",
    "實習教室": "",
    "上課教師": "陳文英等",
    "實習教師": "",
    "開課單位": "獸醫系",
    "開課人數": "80",
    "外系人數": "",
    "可加選餘額": "80",
    "授課語言": "中文",
    "備註": "Z"
  },
  {
    "標題": "學年期：1141 系所名稱:獸醫學系學士班 年級:4 班別:B",
    "必選別": "選修",
    "選課號碼": "4051",
    "科目名稱": "小動物自體免疫疾病概論 b\nIntroduction to autoimmune diseases in small animals",
    "先修科目": "",
    "全半年": "半",
    "學分數": "1",
    "上課時數": "1",
    "實習時數": "",
    "上課時間": "*",
    "實習時間": "",
    "上課教室": "*",
    "實習教室": "",
    "上課教師": "林荀龍等",
    "實習教師": "",
    "開課單位": "獸醫系",
    "開課人數": "50",
    "外系人數": "",
    "可加選餘額": "50",
    "授課語言": "中文",
    "備註": ""
  },
  {
    "標題": "學年期：1141 系所名稱:獸醫學系學士班 年級:4 班別:B",
    "必選別": "必修",
    "選課號碼": "4119",
    "科目名稱": "豬病學 a\nDiseases of Swine",
    "先修科目": "",
    "全半年": "半",
    "學分數": "3",
    "上課時數": "3",
    "實習時數": "",
    "上課時間": "5234",
    "實習時間": "",
    "上課教室": "QE304",
    "實習教室": "",
    "上課教師": "楊程堯等",
    "實習教師": "",
    "開課單位": "獸醫系",
    "開課人數": "120",
    "外系人數": "",
    "可加選餘額": "120",
    "授課語言": "中文",
    "備註": "Z"
  },
  {
    "標題": "學年期：1141 系所名稱:獸醫學系學士班 年級:4 班別:B",
    "必選別": "必修",
    "選課號碼": "4121",
    "科目名稱": "禽病學 a\nDiseases of Poultry",
    "先修科目": "",
    "全半年": "半",
    "學分數": "3",
    "上課時數": "3",
    "實習時數": "",
    "上課時間": "5567",
    "實習時間": "",
    "上課教室": "QE304",
    "實習教室": "",
    "上課教師": "王之仰等",
    "實習教師": "",
    "開課單位": "獸醫系",
    "開課人數": "120",
    "外系人數": "",
    "可加選餘額": "120",
    "授課語言": "中文",
    "備註": "Z"
  },
  {
    "標題": "學年期：1141 系所名稱:獸醫學系學士班 年級:4 班別:B",
    "必選別": "必修",
    "選課號碼": "4126",
    "科目名稱": "反芻動物疾病學 a\nDisease of Ruminant",
    "先修科目": "",
    "全半年": "半",
    "學分數": "3",
    "上課時數": "3",
    "實習時數": "",
    "上課時間": "2234",
    "實習時間": "",
    "上課教室": "QE304",
    "實習教室": "",
    "上課教師": "莊士德等",
    "實習教師": "",
    "開課單位": "獸醫系",
    "開課人數": "120",
    "外系人數": "",
    "可加選餘額": "120",
    "授課語言": "中文",
    "備註": "Z"
  },
  {
    "標題": "學年期：1141 系所名稱:獸醫學系學士班 年級:4 班別:B",
    "必選別": "選修",
    "選課號碼": "4128",
    "科目名稱": "基礎中獸醫學\nBasic Theories of Traditional Chinese Veterinary Medicine",
    "先修科目": "",
    "全半年": "半",
    "學分數": "2",
    "上課時數": "2",
    "實習時數": "",
    "上課時間": "334",
    "實習時間": "",
    "上課教室": "QA001",
    "實習教室": "",
    "上課教師": "賴政宏",
    "實習教師": "",
    "開課單位": "獸醫系",
    "開課人數": "80",
    "外系人數": "0",
    "可加選餘額": "80",
    "授課語言": "中文",
    "備註": ""
  },
  {
    "標題": "學年期：1141 系所名稱:獸醫學系學士班 年級:4 班別:B",
    "必選別": "必修",
    "選課號碼": "4129",
    "科目名稱": "水產動物疾病學 a\nDiseases of Aquatic Animal",
    "先修科目": "",
    "全半年": "半",
    "學分數": "3",
    "上課時數": "3",
    "實習時數": "",
    "上課時間": "4789",
    "實習時間": "",
    "上課教室": "QE304",
    "實習教室": "",
    "上課教師": "謝嘉裕",
    "實習教師": "",
    "開課單位": "獸醫系",
    "開課人數": "120",
    "外系人數": "",
    "可加選餘額": "120",
    "授課語言": "中文",
    "備註": "Z"
  },
  {
    "標題": "學年期：1141 系所名稱:獸醫學系學士班 年級:4 班別:B",
    "必選別": "選修",
    "選課號碼": "4149",
    "科目名稱": "小動物臨床診斷學實習 b\nSmall Animal Clinical diagnostics Laboratory",
    "先修科目": "",
    "全半年": "半",
    "學分數": "1",
    "上課時數": "",
    "實習時數": "3",
    "上課時間": "",
    "實習時間": "1234",
    "上課教室": "",
    "實習教室": "QB1101",
    "上課教師": "",
    "實習教師": "夏偉堯等",
    "開課單位": "獸醫系",
    "開課人數": "80",
    "外系人數": "",
    "可加選餘額": "80",
    "授課語言": "中文",
    "備註": ""
  },
  {
    "標題": "學年期：1141 系所名稱:獸醫學系學士班 年級:4 班別:B",
    "必選別": "必修",
    "選課號碼": "4185",
    "科目名稱": "獸醫臨床病理學\nVeterinary Clinical Pathology",
    "先修科目": "",
    "全半年": "半",
    "學分數": "3",
    "上課時數": "3",
    "實習時數": "",
    "上課時間": "2567",
    "實習時間": "",
    "上課教室": "QE304",
    "實習教室": "",
    "上課教師": "周濟眾等",
    "實習教師": "",
    "開課單位": "獸醫系",
    "開課人數": "100",
    "外系人數": "0",
    "可加選餘額": "100",
    "授課語言": "中文",
    "備註": ""
  },
  {
    "標題": "學年期：1141 系所名稱:獸醫學系學士班 年級:4 班別:B",
    "必選別": "必修",
    "選課號碼": "4189",
    "科目名稱": "獸醫臨床病理學實習\nLab of Veterinary Clinical Pathology",
    "先修科目": "",
    "全半年": "半",
    "學分數": "1",
    "上課時數": "",
    "實習時數": "3",
    "上課時間": "",
    "實習時間": "289A",
    "上課教室": "",
    "實習教室": "QE302",
    "上課教師": "",
    "實習教師": "周濟眾等",
    "開課單位": "獸醫系",
    "開課人數": "60",
    "外系人數": "",
    "可加選餘額": "60",
    "授課語言": "中文",
    "備註": ""
  },
  {
    "標題": "學年期：1141 系所名稱:獸醫學系學士班 年級:5 班別:B",
    "必選別": "必修",
    "選課號碼": "5002",
    "科目名稱": "臨床討論 b\nClinical Conference",
    "先修科目": "",
    "全半年": "全",
    "學分數": "2",
    "上課時數": "2",
    "實習時數": "",
    "上課時間": "412",
    "實習時間": "",
    "上課教室": "QB1101",
    "實習教室": "",
    "上課教師": "陳文英等",
    "實習教師": "",
    "開課單位": "獸醫系",
    "開課人數": "120",
    "外系人數": "",
    "可加選餘額": "120",
    "授課語言": "中文",
    "備註": ""
  },
  {
    "標題": "學年期：1141 系所名稱:獸醫學系學士班 年級:5 班別:B",
    "必選別": "必修",
    "選課號碼": "5004",
    "科目名稱": "診療實習 b\nClinical Practice",
    "先修科目": "",
    "全半年": "全",
    "學分數": "5",
    "上課時數": "",
    "實習時數": "15",
    "上課時間": "",
    "實習時間": "*",
    "上課教室": "",
    "實習教室": "*",
    "上課教師": "",
    "實習教師": "陳文英等",
    "開課單位": "獸醫系",
    "開課人數": "60",
    "外系人數": "",
    "可加選餘額": "60",
    "授課語言": "中文",
    "備註": ""
  },
  {
    "標題": "學年期：1141 系所名稱:獸醫學系學士班 年級:5 班別:B",
    "必選別": "必修",
    "選課號碼": "5005",
    "科目名稱": "獸醫流行病學 a\nVeterinary Epidemiology",
    "先修科目": "",
    "全半年": "半",
    "學分數": "2",
    "上課時數": "2",
    "實習時數": "",
    "上課時間": "334",
    "實習時間": "",
    "上課教室": "QB108",
    "實習教室": "",
    "上課教師": "張照勤",
    "實習教師": "",
    "開課單位": "獸醫系",
    "開課人數": "120",
    "外系人數": "",
    "可加選餘額": "120",
    "授課語言": "中文",
    "備註": "Z"
  },
  {
    "標題": "學年期：1141 系所名稱:獸醫學系學士班 年級:5 班別:B",
    "必選別": "選修",
    "選課號碼": "5010",
    "科目名稱": "小動物眼科學 a\nSmall Animal Ophthalmology",
    "先修科目": "",
    "全半年": "半",
    "學分數": "2",
    "上課時數": "2",
    "實習時數": "",
    "上課時間": "434",
    "實習時間": "",
    "上課教室": "QB201",
    "實習教室": "",
    "上課教師": "林荀龍",
    "實習教師": "",
    "開課單位": "獸醫系",
    "開課人數": "120",
    "外系人數": "",
    "可加選餘額": "120",
    "授課語言": "中文",
    "備註": "Z"
  }
]